geff/__init__.py
geff/_cli.py
geff/_path.py
geff/_typing.py
geff/py.typed
geff/_graph_libs/README.md
geff/_graph_libs/__init__.py
geff/_graph_libs/_api_wrapper.py
geff/_graph_libs/_backend_protocol.py
geff/_graph_libs/_errors.py
geff/_graph_libs/_graph_adapter.py
geff/_graph_libs/_networkx.py
geff/_graph_libs/_rustworkx.py
geff/_graph_libs/_spatial_graph.py
geff/convert/__init__.py
geff/convert/_ctc.py
geff/convert/_dataframe.py
geff/convert/_trackmate_xml.py
geff/core_io/__init__.py
geff/core_io/_base_read.py
geff/core_io/_base_write.py
geff/core_io/_serialization.py
geff/core_io/_utils.py
geff/testing/__init__.py
geff/testing/_utils.py
geff/testing/data.py
geff/validate/__init__.py
geff/validate/data.py
geff/validate/graph.py
geff/validate/segmentation.py
geff/validate/shapes.py
geff/validate/structure.py
geff/validate/tracks.py
geff-1.1.3.1.1.dist-info/METADATA
geff-1.1.3.1.1.dist-info/WHEEL
geff-1.1.3.1.1.dist-info/entry_points.txt
geff-1.1.3.1.1.dist-info/licenses/LICENSE
geff-1.1.3.1.1.dist-info/RECORD
