Metadata-Version: 2.4
Name: geff
Version: 1.1.3.1.1
Summary: Reference implementation of the Graph Exchange File Format
Project-URL: repository, https://github.com/live-image-tracking-tools/geff
Project-URL: homepage, https://github.com/live-image-tracking-tools/geff
Project-URL: documentation, https://liveimagetrackingtools.org/geff/
License-Expression: MIT
License-File: LICENSE
Classifier: Development Status :: 3 - Alpha
Classifier: Natural Language :: English
Classifier: Programming Language :: Python :: 3
Classifier: Programming Language :: Python :: 3.10
Classifier: Programming Language :: Python :: 3.11
Classifier: Programming Language :: Python :: 3.12
Classifier: Programming Language :: Python :: 3.13
Requires-Python: >=3.10
Requires-Dist: geff-spec<=1.1
Requires-Dist: networkx>=3.2.1
Requires-Dist: numcodecs<0.16,>=0.13; python_version == '3.10'
Requires-Dist: numcodecs>=0.13
Requires-Dist: numcodecs>=0.15; python_version >= '3.13'
Requires-Dist: numpy>=1.24
Requires-Dist: numpy>=1.26; python_version >= '3.12'
Requires-Dist: numpy>=2.1; python_version >= '3.13'
Requires-Dist: pydantic>=2.11
Requires-Dist: typer>=0.14.0
Requires-Dist: zarr<4,>=2.18
Provides-Extra: ctc
Requires-Dist: dask>=2024.10; extra == 'ctc'
Requires-Dist: imagecodecs>=2025.3.30; extra == 'ctc'
Requires-Dist: scikit-image>=0.23.2; extra == 'ctc'
Requires-Dist: scikit-image>=0.25; (python_version >= '3.13') and extra == 'ctc'
Requires-Dist: tifffile>=2024.10; extra == 'ctc'
Provides-Extra: pandas
Requires-Dist: pandas>=2; extra == 'pandas'
Requires-Dist: pandas>=2.3; (python_version >= '3.12') and extra == 'pandas'
Provides-Extra: rx
Requires-Dist: rustworkx>=0.16.0; extra == 'rx'
Provides-Extra: spatial-graph
Requires-Dist: spatial-graph>=0.0.4; extra == 'spatial-graph'
